{"scripts":[{"typewriter":{"speedUp":0.01,"speed":0.05},"nameColor":"#a9f548","say":"みんなー！見て見て～！","dir":1,"actorName":"キズナアイ","side":2,"painting":{"time":1,"alpha":0.3},"bgName":"bg_story_ailevel","actor":10400030},{"typewriter":{"speedUp":0.01,"speed":0.05},"side":2,"painting":{"time":1,"alpha":0.3},"say":"おぉ、また新しい衣装を取り戻したのですね","actor":301050,"dir":1,"bgName":"bg_story_ailevel","nameColor":"#a9f548"},{"typewriter":{"speedUp":0.01,"speed":0.05},"side":2,"painting":{"time":1,"alpha":0.3},"say":"かわいい～！フリフリがたくさんついててお姫様みたい～！アイちゃん、すっごく似合ってるよ！","actor":201210,"dir":1,"bgName":"bg_story_ailevel","nameColor":"#a9f548"},{"typewriter":{"speedUp":0.01,"speed":0.05},"side":2,"painting":{"time":1,"alpha":0.3},"say":"なるほどね！こういうのが「まごにもいしょう」ってやつなんだよね！雷もかわいいと思う！","actor":301110,"dir":1,"bgName":"bg_story_ailevel","nameColor":"#a9f548"},{"expression":4,"nameColor":"#a9f548","say":"えへへー、ありがとー！","dir":1,"actorName":"キズナアイ","side":2,"painting":{"time":1,"alpha":0.3},"typewriter":{"speedUp":0.01,"speed":0.05},"bgName":"bg_story_ailevel","actor":10400030},{"typewriter":{"speedUp":0.01,"speed":0.05},"nameColor":"#a9f548","say":"みんな、大変にゃ！新しい衣装で和んでる場合じゃないにゃ！","dir":1,"side":2,"action":[{"type":"shake","y":45,"delay":0,"dur":0.15,"number":2,"x":0}],"painting":{"time":1,"alpha":0.3},"bgName":"bg_story_ailevel","actor":312010},{"typewriter":{"speedUp":0.01,"speed":0.05},"side":2,"painting":{"time":1,"alpha":0.3},"say":"明石？慌ててどうしたの？","actor":101170,"dir":1,"bgName":"bg_story_ailevel","nameColor":"#a9f548"},{"typewriter":{"speedUp":0.01,"speed":0.05},"side":2,"painting":{"time":1,"alpha":0.3},"say":"新しいバーチャル鏡面海域が出現したのにゃ！","actor":312010,"dir":1,"bgName":"bg_story_ailevel","nameColor":"#a9f548"},{"typewriter":{"speedUp":0.01,"speed":0.05},"side":2,"painting":{"time":1,"alpha":0.3},"say":"放っておくとウィルスがどんどん増えて大変な事にってしまうぞ。みんな急いで向かってほしい","actor":302010,"dir":1,"bgName":"bg_story_ailevel","nameColor":"#a9f548"},{"typewriter":{"speedUp":0.01,"speed":0.05},"side":2,"painting":{"time":1,"alpha":0.3},"say":"今回のバーチャル鏡面海域はいつもと違う感じになるかもしれないから、念のためにこれを装備していくにゃ","actor":312010,"dir":1,"bgName":"bg_story_ailevel","nameColor":"#a9f548"},{"typewriter":{"speedUp":0.01,"speed":0.05},"nameColor":"#a9f548","say":"ありがと明石ちゃん！みんな急いで向かおう！","dir":1,"actorName":"キズナアイ","side":2,"painting":{"time":1,"alpha":0.3},"bgName":"bg_story_ailevel","actor":10400030},{"typewriter":{"speedUp":0.01,"speed":0.05},"side":2,"say":"バーチャル鏡面海域・高度4000メートル上空","dir":1,"painting":{"time":1,"alpha":0.3},"bgName":"bg_story_ailevel","flashN":{"alpha":[[0,1,0.5],[1,0,0.5,0.5]],"color":[1,1,1]}},{"typewriter":{"speedUp":0.01,"speed":0.05},"nameColor":"#a9f548","say":"…………へ？","dir":1,"actorName":"キズナアイ","side":2,"painting":{"time":1,"alpha":0.3},"bgName":"bg_story_ailevel","actor":10400030},{"expression":2,"nameColor":"#a9f548","say":"き゛ゃ゛あ゛あ゛あ゛あ゛あ゛あ゛あ゛ぁ゛ぁ゛ぁ゛！な゛ん゛て゛こ゛ん゛な゛た゛か゛い゛と゛こ゛ろ゛に゛ワ゛ープ゛し゛て゛る゛の゛お゛お゛お゛ぉ゛ぉ゛ぉ゛！","dir":1,"actorName":"キズナアイ","side":2,"action":[{"type":"move","y":-2250,"delay":0.5,"dur":0.5,"x":0}],"painting":{"time":1,"alpha":0.3},"typewriter":{"speedUp":0.01,"speed":0.05},"bgName":"bg_story_ailevel","actor":10400030},{"typewriter":{"speedUp":0.01,"speed":0.05},"nameColor":"#a9f548","say":"おーーーーーちーーーーーるーーーーー！！！","dir":1,"side":2,"action":[{"type":"move","y":-2250,"delay":0,"dur":1,"x":0}],"painting":{"time":1,"alpha":0.3},"bgName":"bg_story_ailevel","actor":201210},{"typewriter":{"speedUp":0.01,"speed":0.05},"nameColor":"#a9f548","say":"ひゃあああああぁぁぁぁぁぁぁ！","dir":1,"side":2,"action":[{"type":"move","y":-2250,"delay":0,"dur":1,"x":0}],"painting":{"time":1,"alpha":0.3},"bgName":"bg_story_ailevel","actor":401230},{"expression":6,"nameColor":"#a9f548","say":"ラフィーちゃん助けてえええええええ！","dir":1,"actorName":"キズナアイ","side":2,"action":[{"type":"move","y":-2250,"delay":0,"dur":1,"x":0}],"painting":{"time":1,"alpha":0.3},"typewriter":{"speedUp":0.01,"speed":0.05},"bgName":"bg_story_ailevel","actor":10400030},{"typewriter":{"speedUp":0.01,"speed":0.05},"nameColor":"#a9f548","say":"（気絶）","dir":1,"side":2,"action":[{"type":"move","y":-2250,"delay":0,"dur":1,"x":0}],"painting":{"time":1,"alpha":0.3},"bgName":"bg_story_ailevel","actor":101170},{"expression":5,"nameColor":"#a9f548","say":"って気絶してるーーーー！？","dir":1,"actorName":"キズナアイ","side":2,"painting":{"time":1,"alpha":0.3},"typewriter":{"speedUp":0.01,"speed":0.05},"bgName":"bg_story_ailevel","actor":10400030},{"typewriter":{"speedUp":0.01,"speed":0.05},"side":2,"painting":{"time":1,"alpha":0.3},"say":"はっ、こんな時こそさっき明石からもらった装備の出番ですよ！","actor":401230,"dir":1,"bgName":"bg_story_ailevel","nameColor":"#a9f548"},{"typewriter":{"speedUp":0.01,"speed":0.05},"side":2,"painting":{"time":1,"alpha":0.3},"say":"そういえばそんなものも――明石特製エアボーン展開……です！","actor":301050,"dir":1,"bgName":"bg_story_ailevel","nameColor":"#a9f548"},{"flashout":{"dur":0.5,"alpha":[0,1],"black":true},"side":2,"say":"………","dir":1,"painting":{"time":1,"alpha":0.3},"flashin":{"delay":0.5,"dur":0.5,"alpha":[1,0],"black":true},"typewriter":{"speedUp":0.01,"speed":0.05}},{"typewriter":{"speedUp":0.01,"speed":0.05},"side":2,"say":"ふぅ、無事着水できてよかったです","actor":301120,"painting":{"time":1,"alpha":0.3},"dir":1,"nameColor":"#a9f548"},{"expression":3,"nameColor":"#a9f548","say":"もうだめかと思った～","dir":1,"actorName":"キズナアイ","side":2,"painting":{"time":1,"alpha":0.3},"typewriter":{"speedUp":0.01,"speed":0.05},"actor":10400030},{"typewriter":{"speedUp":0.01,"speed":0.05},"side":2,"say":"自動で展開してくれるタイプで助かった…明石に感謝","actor":101170,"painting":{"time":1,"alpha":0.3},"dir":1,"nameColor":"#a9f548"},{"typewriter":{"speedUp":0.01,"speed":0.05},"side":2,"say":"あれ？でもなんか周りの霧みたいなのがだんだんこっちに迫ってきてるような・・・？","actor":201210,"painting":{"time":1,"alpha":0.3},"dir":1,"nameColor":"#a9f548"},{"typewriter":{"speedUp":0.01,"speed":0.05},"side":2,"say":"何でしょうか・・・？とにかく危険なにおいがしますね","actor":401230,"painting":{"time":1,"alpha":0.3},"dir":1,"nameColor":"#a9f548"},{"typewriter":{"speedUp":0.01,"speed":0.05},"side":2,"say":"なるほどね！あれに飲み込まれると「ダメージ」をうけちゃうかもしれないね！","actor":301110,"painting":{"time":1,"alpha":0.3},"dir":1,"nameColor":"#a9f548"},{"expression":2,"nameColor":"#a9f548","say":"（ゾクッ）あれ…？このシチュエーション、どこかで……？","dir":1,"actorName":"キズナアイ","side":2,"action":[{"type":"shake","y":22.5,"delay":0,"dur":0.15,"number":3,"x":0}],"painting":{"time":1,"alpha":0.3},"typewriter":{"speedUp":0.01,"speed":0.05},"actor":10400030},{"expression":6,"nameColor":"#a9f548","say":"私のインテリジェンスな勘が、全力で海域中心部に向かって逃げろって言ってる！！","dir":1,"actorName":"キズナアイ","side":2,"painting":{"time":1,"alpha":0.3},"typewriter":{"speedUp":0.01,"speed":0.05},"actor":10400030},{"typewriter":{"speedUp":0.01,"speed":0.05},"side":2,"say":"飲み込まれないように、気を付けて行きましょう","actor":301120,"painting":{"time":1,"alpha":0.3},"dir":1,"nameColor":"#a9f548"}],"once":true,"mode":2,"fadein":1.5,"id":"AIGUANQIA11"}