{"fadeType":1,"once":true,"scripts":[{"mode":1,"sequence":[["幽霊さんはガンバラナイ\n\n<size=45>その六　大失敗！<\/size>",1]]},{"typewriter":{"speedUp":0.01,"speed":0.05},"side":2,"say":"うう……ま、負けた……ノーカンだ！い、今のは油断しただけなの――！","actor":106011,"painting":{"time":1,"alpha":0.3},"dir":1,"nameColor":"#a9f548"},{"typewriter":{"speedUp":0.01,"speed":0.05},"side":2,"say":"え？素直に負けを認めろって？","actor":106011,"painting":{"time":1,"alpha":0.3},"dir":1,"nameColor":"#a9f548"},{"typewriter":{"speedUp":0.01,"speed":0.05},"side":2,"say":"そ、そりゃ…指揮官が一回勝ったら訓練に行くって言ったけど……で、でも今のはノーカンなの――！","actor":106011,"painting":{"time":1,"alpha":0.3},"dir":1,"nameColor":"#a9f548"},{"typewriter":{"speedUp":0.01,"speed":0.05},"side":2,"say":"嫌なの――！出掛けたくないの――！休暇中なのに――！","actor":106011,"painting":{"time":1,"alpha":0.3},"dir":1,"nameColor":"#a9f548"}],"mode":2,"fadein":1.5,"id":"CHANGDAO6","fadeOut":1.5}