{"fadeType":1,"once":true,"scripts":[{"sequence":[["刻む時間すら霞む、永遠に続く輪廻",2],["不確なる確率変動、偶然と必然の事象収束",3],["定命あるものを繋ぎ止める「伝承」の転結……",6],["……",7],["あのデアイがなかったら",8],["別のシュウマツがあるのダろうカ",10],["……",12],["アナタデスカ？「ソウゾウシュ」サマ？",13]]},{"sequence":[["期間限定イベント・紅染の来訪者",2]]},{"typewriter":{"speedUp":0.01,"speed":0.05},"nameColor":"#a9f548","withoutPainting":true,"blackBg":true,"actorName":"？？？","side":0,"mode":2,"painting":{"time":1,"alpha":0.3},"say":"嵐が激しいわ！このまま進んだら全滅よ！","actor":900011},{"typewriter":{"speedUp":0.01,"speed":0.05},"nameColor":"#a9f548","withoutPainting":true,"blackBg":true,"actorName":"？？？","side":1,"mode":2,"painting":{"time":1,"alpha":0.3},"say":"あんな代価を払ったのに、このまま諦めるわけにはいかないわ！私を信じて！もうすぐ嵐を突破できるわ！","actor":900012},{"typewriter":{"speedUp":0.01,"speed":0.05},"nameColor":"#a9f548","withoutPainting":true,"blackBg":true,"actorName":"？？？","side":0,"mode":2,"painting":{"time":1,"alpha":0.3},"say":"前方未確認反応！方角150！緊急回避……","actor":900011},{"typewriter":{"speedUp":0.01,"speed":0.05},"nameColor":"#a9f548","withoutPainting":true,"blackBg":true,"actorName":"？？？","side":1,"mode":2,"painting":{"time":1,"alpha":0.3},"say":"未確認反応？この嵐の中で？位置を教えて！","actor":900012},{"typewriter":{"speedUp":0.01,"speed":0.05},"nameColor":"#a9f548","withoutPainting":true,"blackBg":true,"actorName":"？？？","side":0,"mode":2,"painting":{"time":1,"alpha":0.3},"say":"…………","actor":900011},{"typewriter":{"speedUp":0.01,"speed":0.05},"nameColor":"#a9f548","withoutPainting":true,"blackBg":true,"actorName":"？？？","side":1,"mode":2,"painting":{"time":1,"alpha":0.3},"say":"翔鶴姉、早く位置を教えて！","actor":900012},{"typewriter":{"speedUp":0.01,"speed":0.05},"nameColor":"#a9f548","withoutPainting":true,"blackBg":true,"actorName":"？？？","side":0,"mode":2,"painting":{"time":1,"alpha":0.3},"say":"…………","actor":900011},{"typewriter":{"speedUp":0.01,"speed":0.05},"nameColor":"#a9f548","withoutPainting":true,"blackBg":true,"actorName":"？？？","side":0,"mode":2,"painting":{"time":1,"alpha":0.3},"say":"…………","actor":900011},{"typewriter":{"speedUp":0.01,"speed":0.05},"nameColor":"#a9f548","withoutPainting":true,"blackBg":true,"actorName":"？？？","side":0,"mode":2,"painting":{"time":1,"alpha":0.3},"say":"……ニゲ…テ…………","actor":900011},{"typewriter":{"speedUp":0.01,"speed":0.05},"nameColor":"#a9f548","withoutPainting":true,"blackBg":true,"actorName":"？？？","side":1,"mode":2,"painting":{"time":1,"alpha":0.3},"say":"無線封止エリアに入った！？今回は…やばいかも……","actor":900012},{"typewriter":{"speedUp":0.01,"speed":0.05},"nameColor":"#a9f548","withoutPainting":true,"blackBg":true,"actorName":"？？？","side":1,"mode":2,"painting":{"time":1,"alpha":0.3},"say":"あの人との勝負がまだついていないというのに…","actor":900012},{"typewriter":{"speedUp":0.01,"speed":0.05},"nameColor":"#a9f548","withoutPainting":true,"blackBg":true,"actorName":"？？？","side":1,"mode":2,"painting":{"time":1,"alpha":0.3},"say":"！？この光は……？","actor":900012},{"typewriter":{"speedUp":0.01,"speed":0.05},"nameColor":"#a9f548","withoutPainting":true,"blackBg":true,"actorName":"？？？","side":1,"mode":2,"painting":{"time":1,"alpha":0.3},"say":"！！！","actor":900012},{"flashout":{"alpha":[0,1],"dur":1.5},"nameColor":"#a9f548","say":"……","blackBg":true,"side":2,"painting":{"time":1,"alpha":0.3},"mode":2,"typewriter":{"speedUp":0.01,"speed":0.05},"flashin":{"delay":2,"dur":1.5,"alpha":[1,0]},"actor":307060},{"typewriter":{"speedUp":0.01,"speed":0.05},"nameColor":"#a9f548","painting":{"time":1,"alpha":0.3},"say":"……ここは…？","actor":307060,"blackBg":true,"side":2,"mode":2},{"typewriter":{"speedUp":0.01,"speed":0.05},"nameColor":"#a9f548","painting":{"time":1,"alpha":0.3},"say":"私、今回も沈まなかったわ！！","actor":307060,"blackBg":true,"side":2,"mode":2},{"typewriter":{"speedUp":0.01,"speed":0.05},"nameColor":"#a9f548","painting":{"time":1,"alpha":0.3},"say":"くっ！…頭が…今何が起きたか思い出せない…","actor":307060,"blackBg":true,"side":2,"mode":2},{"typewriter":{"speedUp":0.01,"speed":0.05},"nameColor":"#a9f548","painting":{"time":1,"alpha":0.3},"say":"もう……翔鶴姉と連絡がつかない…状況が全然良くなってないじゃない…","actor":307060,"blackBg":true,"side":2,"mode":2},{"typewriter":{"speedUp":0.01,"speed":0.05},"nameColor":"#a9f548","painting":{"time":1,"alpha":0.3},"say":"……","actor":307060,"blackBg":true,"side":2,"mode":2},{"typewriter":{"speedUp":0.01,"speed":0.05},"nameColor":"#a9f548","painting":{"time":1,"alpha":0.3},"say":"ううん、そんなことはないわ。だってようやくここ…","actor":307060,"blackBg":true,"side":2,"mode":2},{"typewriter":{"speedUp":0.01,"speed":0.05},"nameColor":"#a9f548","painting":{"time":1,"alpha":0.3},"say":"「聖域」に、辿り着いたんだから！","actor":307060,"blackBg":true,"side":2,"mode":2}],"mode":1,"occlusion":2,"id":"GUOQING1","fadeOut":0.5}