{"fadeType":2,"once":true,"scripts":[{"mode":1,"stopbgm":true,"sequence":[["軽空母龍驤ここにあり\n\n<size=45>六 宿敵！？伝説のアイドルとは<\/size>",1]]},{"expression":3,"nameColor":"#a9f548","say":"殿は今何しているのでしょうか……","dir":1,"bgm":"story-1","painting":{"time":1,"alpha":0.3},"side":2,"bgmDelay":2,"typewriter":{"speedUp":0.01,"speed":0.05},"flashin":{"delay":1,"dur":1,"alpha":[1,0],"black":true},"flashout":{"dur":1,"alpha":[0,1],"black":true},"bgName":"bg_story_school","actor":306060},{"typewriter":{"speedUp":0.01,"speed":0.05},"nameColor":"#a9f548","say":"ジャジャーン！艦載機によるサプライズ攻撃！","dir":1,"side":2,"action":[{"type":"shake","y":45,"delay":0.2,"dur":0.2,"number":2,"x":0}],"soundeffect":"event:\/battle\/plane","painting":{"time":1,"alpha":0.3},"bgName":"bg_story_school","actor":107030},{"expression":3,"nameColor":"#a9f548","say":"はあ………","dir":1,"side":2,"painting":{"time":1,"alpha":0.3},"typewriter":{"speedUp":0.01,"speed":0.05},"bgName":"bg_story_school","actor":306060},{"typewriter":{"speedUp":0.01,"speed":0.05},"nameColor":"#a9f548","paintingFadeOut":{"side":0,"time":0.5},"say":"あ、あれ？龍驤ちゃん？今日はノリ悪いよ…？","dir":1,"side":1,"painting":{"time":1,"alpha":0.3},"bgName":"bg_story_school","actor":107030},{"expression":3,"nameColor":"#a9f548","say":"サラトガさん……今日はそちらの悪戯に付き合う気分じゃありません。ご容赦を","dir":1,"side":0,"painting":{"time":1,"alpha":0.3},"typewriter":{"speedUp":0.01,"speed":0.05},"bgName":"bg_story_school","actor":306060},{"typewriter":{"speedUp":0.01,"speed":0.05},"side":1,"painting":{"time":1,"alpha":0.3},"say":"そう…？じゃあこのサラトガちゃんがお悩み解決してあげるよ！","actor":107030,"dir":1,"bgName":"bg_story_school","nameColor":"#a9f548"},{"typewriter":{"speedUp":0.01,"speed":0.05},"side":0,"painting":{"time":1,"alpha":0.3},"say":"そ、そういうわけにはいきません！サラトガさんはユニオンの空母、自分は……","actor":306060,"dir":1,"bgName":"bg_story_school","nameColor":"#a9f548"},{"expression":1,"nameColor":"#a9f548","say":"同じ艦隊の仲間なので敵ではありませんが、だからといって簡単に気を許す相手ではありませぬぞ！","dir":1,"side":0,"action":[{"type":"shake","y":45,"delay":0.2,"dur":0.15,"number":2,"x":0}],"painting":{"time":1,"alpha":0.3},"typewriter":{"speedUp":0.01,"speed":0.05},"bgName":"bg_story_school","actor":306060},{"typewriter":{"speedUp":0.01,"speed":0.05},"side":2,"painting":{"time":1,"alpha":0.3},"say":"聞けばこの間、殿にレキシントンさんとの「らいぶ」とやらのチケットを手渡しに行ったそうじゃありませんか！","actor":306060,"dir":1,"bgName":"bg_story_school","nameColor":"#a9f548"},{"expression":1,"nameColor":"#a9f548","say":"殿の大事な勤務時間を奪うなど、秘書艦として自分は断じて許せませんっ！","dir":1,"side":2,"painting":{"time":1,"alpha":0.3},"typewriter":{"speedUp":0.01,"speed":0.05},"bgName":"bg_story_school","actor":306060},{"typewriter":{"speedUp":0.01,"speed":0.05},"nameColor":"#a9f548","say":"…………ずばり、宿敵（ライバル）です！","dir":1,"side":2,"action":[{"type":"shake","y":45,"delay":0.2,"dur":0.15,"number":2,"x":0}],"painting":{"time":1,"alpha":0.3},"bgName":"bg_story_school","actor":306060},{"typewriter":{"speedUp":0.01,"speed":0.05},"side":2,"painting":{"time":1,"alpha":0.3},"say":"なるほど、恋わずらいだ","actor":107030,"dir":1,"bgName":"bg_story_school","nameColor":"#a9f548"},{"expression":3,"nameColor":"#a9f548","say":"え？","dir":1,"side":2,"painting":{"time":1,"alpha":0.3},"typewriter":{"speedUp":0.01,"speed":0.05},"bgName":"bg_story_school","actor":306060},{"typewriter":{"speedUp":0.01,"speed":0.05},"nameColor":"#a9f548","paintingFadeOut":{"side":0,"time":0.5},"say":"わかった。つまるところ龍驤ちゃんは指揮官にいいところを見てほしいって思ってるわけね","dir":1,"side":1,"painting":{"time":1,"alpha":0.3},"bgName":"bg_story_school","actor":107030},{"expression":4,"nameColor":"#a9f548","say":"なっ！？","dir":1,"side":0,"action":[{"type":"shake","y":45,"delay":0.2,"dur":0.15,"number":2,"x":0}],"painting":{"time":1,"alpha":0.3},"typewriter":{"speedUp":0.01,"speed":0.05},"bgName":"bg_story_school","actor":306060},{"typewriter":{"speedUp":0.01,"speed":0.05},"side":1,"painting":{"time":1,"alpha":0.3},"say":"話は聞いたよ？確かにアレはちょっと災難だったけど、指揮官はそんなに心が狭い人間ではないからね！","actor":107030,"dir":1,"bgName":"bg_story_school","nameColor":"#a9f548"},{"typewriter":{"speedUp":0.01,"speed":0.05},"side":1,"painting":{"time":1,"alpha":0.3},"say":"だから、いっそコクっちゃってもいいぐらい、指揮官に本当の気持ちを伝えたほうがいいって！","actor":107030,"dir":1,"bgName":"bg_story_school","nameColor":"#a9f548"},{"expression":4,"nameColor":"#a9f548","say":"そ、そんなの自分には………","dir":1,"side":0,"action":[{"type":"shake","y":0,"delay":0.2,"dur":0.4,"number":2,"x":60}],"painting":{"time":1,"alpha":0.3},"typewriter":{"speedUp":0.01,"speed":0.05},"bgName":"bg_story_school","actor":306060},{"typewriter":{"speedUp":0.01,"speed":0.05},"side":1,"painting":{"time":1,"alpha":0.3},"say":"きっと大丈夫！サラトガちゃん、みんなの恋も応援しているからね♪","actor":107030,"dir":1,"bgName":"bg_story_school","nameColor":"#a9f548"},{"expression":3,"nameColor":"#a9f548","say":"サラトガさん…………","dir":1,"side":0,"painting":{"time":1,"alpha":0.3},"typewriter":{"speedUp":0.01,"speed":0.05},"actor":306060,"bgName":"bg_story_school","blackBg":true}],"mode":2,"fadein":1.5,"id":"LONGXIANG6","fadeOut":1.5}