{"fadeType":1,"once":true,"scripts":[{"expression":2,"nameColor":"#a9f548","say":"負けた、です…でも楽しかったです","dir":1,"bgm":"azumaster-ins","side":2,"painting":{"time":1,"alpha":0.3},"typewriter":{"speedUp":0.01,"speed":0.05},"actor":301057},{"typewriter":{"speedUp":0.01,"speed":0.05},"side":2,"say":"「μ兵装」の性能はさておき、こうしてステージのことを考えながら戦うと、いつもとは違う感じがします","actor":401236,"painting":{"time":1,"alpha":0.3},"dir":1,"nameColor":"#a9f548"},{"typewriter":{"speedUp":0.01,"speed":0.05},"side":2,"say":"「艦船として戦う」ことより、「みんなと一緒に楽しみたい」気持ちが強くて、結果的にいつもより実力を発揮できた気がするんです","actor":401236,"painting":{"time":1,"alpha":0.3},"dir":1,"nameColor":"#a9f548"},{"typewriter":{"speedUp":0.01,"speed":0.05},"side":2,"action":[{"type":"shake","y":30,"delay":0,"dur":0.15,"number":2,"x":0}],"say":"ふふん！サラトガちゃんの特訓も効果があったみたいね！","actor":107039,"painting":{"time":1,"alpha":0.3},"dir":1,"nameColor":"#a9f548"},{"typewriter":{"speedUp":0.01,"speed":0.05},"side":2,"say":"はい、駆逐艦2隻でここまで戦えたのは意外、です","actor":301057,"painting":{"time":1,"alpha":0.3},"dir":1,"nameColor":"#a9f548"},{"typewriter":{"speedUp":0.01,"speed":0.05},"side":2,"say":"綾波、そろそろジャベリンたちと合流しましょ？","actor":401236,"painting":{"time":1,"alpha":0.3},"dir":1,"nameColor":"#a9f548"},{"typewriter":{"speedUp":0.01,"speed":0.05},"side":2,"action":[{"type":"shake","y":30,"delay":0,"dur":0.15,"number":2,"x":0}],"say":"あっ、「ポラリス」の皆さんはこちらを気にせず次の実験項目に移行してください！","actor":401236,"painting":{"time":1,"alpha":0.3},"dir":1,"nameColor":"#a9f548"},{"flashout":{"dur":1,"alpha":[0,1],"black":true},"nameColor":"#a9f548","say":"「μ兵装」の戦闘実験においてのパフォーマンス、カタログスペックと差異があると認む","dir":1,"side":2,"painting":{"time":1,"alpha":0.3},"typewriter":{"speedUp":0.01,"speed":0.05},"flashin":{"delay":1,"dur":1,"alpha":[1,0],"black":true},"actor":905030},{"expression":4,"nameColor":"#a9f548","painting":{"time":1,"alpha":0.3},"say":"艤装の性能が普段身につけているものと違うのはわかるけど、なんだかこう、微妙に戦いやすいというか…","dir":1,"typewriter":{"speedUp":0.01,"speed":0.05},"actor":102240,"side":2},{"expression":2,"nameColor":"#a9f548","painting":{"time":1,"alpha":0.3},"say":"同感ですね。艦船である私達の艤装は決まった性能しか発揮できないはずです","dir":1,"typewriter":{"speedUp":0.01,"speed":0.05},"actor":202250,"side":2},{"expression":2,"nameColor":"#a9f548","say":"ガスコーニュ自身の戦闘行動のパターンはリハーサル及びシミュレーション時から変化なしと認む","dir":1,"side":2,"action":[{"type":"shake","y":30,"delay":0,"dur":0.15,"number":2,"x":0}],"painting":{"time":1,"alpha":0.3},"typewriter":{"speedUp":0.01,"speed":0.05},"actor":905030},{"expression":4,"nameColor":"#a9f548","painting":{"time":1,"alpha":0.3},"say":"んーそれってガスコーニュは別に戦い方を変えてないのに、艤装を使う肌感覚はいつもより若干細かいところで色々と変わるってこと？","dir":1,"typewriter":{"speedUp":0.01,"speed":0.05},"actor":102240,"side":2},{"expression":2,"nameColor":"#a9f548","painting":{"time":1,"alpha":0.3},"say":"はい","dir":1,"typewriter":{"speedUp":0.01,"speed":0.05},"actor":905030,"side":2},{"typewriter":{"speedUp":0.01,"speed":0.05},"side":2,"say":"ガスコーニュが言うと説得力があるわね…この「μ兵装」、どうやら私達の知ってる「艤装」とはちょっと違うわね","actor":403070,"painting":{"time":1,"alpha":0.3},"dir":1,"nameColor":"#a9f548"},{"typewriter":{"speedUp":0.01,"speed":0.05},"side":2,"say":"………………","actor":307100,"painting":{"time":1,"alpha":0.3},"dir":1,"nameColor":"#a9f548"},{"typewriter":{"speedUp":0.01,"speed":0.05},"side":2,"say":"（やっぱりそうね…私達「艦船」の艤装の性能はどうであれ、リュウコツとの適合性がある以上大きく変わらないはず）","actor":307100,"painting":{"time":1,"alpha":0.3},"dir":1,"nameColor":"#a9f548"},{"typewriter":{"speedUp":0.01,"speed":0.05},"side":2,"say":"（これらの「μ兵装」も、今日の本番が来るまでは性能のブレが全部許容範囲だった…）","actor":307100,"painting":{"time":1,"alpha":0.3},"dir":1,"nameColor":"#a9f548"},{"typewriter":{"speedUp":0.01,"speed":0.05},"side":2,"say":"（つまりこのような現象は出現していなかった）","actor":307100,"painting":{"time":1,"alpha":0.3},"dir":1,"nameColor":"#a9f548"},{"typewriter":{"speedUp":0.01,"speed":0.05},"side":2,"say":"（ならこの現象の裏にはなんらかの理由がある……それは一体どういうことなのかしら）","actor":307100,"painting":{"time":1,"alpha":0.3},"dir":1,"nameColor":"#a9f548"},{"typewriter":{"speedUp":0.01,"speed":0.05},"side":2,"say":"参考情報としての信頼性が低レベルではあるが","actor":905030,"painting":{"time":1,"alpha":0.3},"dir":1,"nameColor":"#a9f548"},{"typewriter":{"speedUp":0.01,"speed":0.05},"side":2,"say":"対「セイレーン」における戦術プロトコル、艤装の出力の安定化のため、感情モジュールの稼働抑制を行っている","actor":905030,"painting":{"time":1,"alpha":0.3},"dir":1,"nameColor":"#a9f548"},{"expression":4,"nameColor":"#a9f548","painting":{"time":1,"alpha":0.3},"say":"先程の兵装実験テストにおける戦闘中、通常の戦闘プロトコルと共通の感情抑制処理を行ったにもかかわらず","dir":1,"typewriter":{"speedUp":0.01,"speed":0.05},"actor":905030,"side":2},{"expression":2,"nameColor":"#a9f548","painting":{"time":1,"alpha":0.3},"say":"感情モジュールの活性化度合いが比較的高いと観測","dir":1,"typewriter":{"speedUp":0.01,"speed":0.05},"actor":905030,"side":2},{"typewriter":{"speedUp":0.01,"speed":0.05},"side":2,"say":"………………","actor":307100,"painting":{"time":1,"alpha":0.3},"dir":1,"nameColor":"#a9f548"},{"expression":4,"nameColor":"#a9f548","painting":{"time":1,"alpha":0.3},"say":"ごめん、今のはあんまりよく分からなかった…","dir":1,"typewriter":{"speedUp":0.01,"speed":0.05},"actor":102240,"side":2},{"expression":1,"nameColor":"#a9f548","painting":{"time":1,"alpha":0.3},"say":"つまり「楽しかった」と感じたのですね","dir":1,"typewriter":{"speedUp":0.01,"speed":0.05},"actor":202250,"side":2},{"typewriter":{"speedUp":0.01,"speed":0.05},"side":2,"say":"回りくどいっての……","actor":403070,"painting":{"time":1,"alpha":0.3},"dir":1,"nameColor":"#a9f548"},{"expression":2,"nameColor":"#a9f548","painting":{"time":1,"alpha":0.3},"say":"説明の仕方について謝罪。「ごめんなさい」","dir":1,"typewriter":{"speedUp":0.01,"speed":0.05},"actor":905030,"side":2},{"expression":2,"nameColor":"#a9f548","painting":{"time":1,"alpha":0.3},"say":"ただ、兵装実験においてガスコーニュの感情モジュールの開放が必要と判断された場合――","dir":1,"typewriter":{"speedUp":0.01,"speed":0.05},"actor":905030,"side":2},{"expression":2,"nameColor":"#a9f548","painting":{"time":1,"alpha":0.3},"say":"どうぞ、ガスコーニュに指示を","dir":1,"typewriter":{"speedUp":0.01,"speed":0.05},"actor":905030,"side":2}],"mode":2,"fadein":1.5,"id":"OUXIANGHUODONG9","fadeOut":1.5}