{"id":"TACT40002","scripts":[{"painting":{"time":1,"alpha":0.3},"typewriter":{"speed":0.05,"speedUp":0.01},"shake":{"speed":1,"number":3},"side":2,"say":"………","actorName":"{namecode:92}","actor":307020,"nameColor":"#ff0000"},{"dir":-1,"say":"居然是来自一航战的精锐航空队，重樱派出你们的目的到底是什么？","nameColor":"#a9f548","painting":{"time":1,"alpha":0.3},"side":0,"paintingFadeOut":{"side":1,"time":0.5},"shake":{"speed":1,"number":3},"actor":502020,"typewriter":{"speed":0.05,"speedUp":0.01}},{"painting":{"time":1,"alpha":0.3},"typewriter":{"speed":0.05,"speedUp":0.01},"shake":{"speed":1,"number":3},"side":1,"say":"………","actorName":"{namecode:92}","actor":307020,"nameColor":"#ff0000"},{"painting":{"time":1,"alpha":0.3},"typewriter":{"speed":0.05,"speedUp":0.01},"shake":{"speed":1,"number":3},"side":0,"dir":-1,"say":"可恶，这是装作听不到么，平海，这一次，不要放过一架飞机！","actor":502020,"nameColor":"#a9f548"},{"painting":{"time":1,"alpha":0.3},"typewriter":{"speed":0.05,"speedUp":0.01},"side":0,"shake":{"speed":1,"number":3},"say":"是！","actor":502030,"nameColor":"#a9f548"}],"fadeOut":1.5,"fadeType":1,"noWaitFade":true,"fadein":1.5,"mode":2,"once":true}