{"fadeType":1,"once":true,"scripts":[{"mode":1,"sequence":[["ワイワイお茶会\n\n<size=45>その二 寂しがり屋の女王さま<\/size>",1]]},{"typewriter":{"speedUp":0.01,"speed":0.05},"side":2,"say":"ベルが紅茶を持っていてよかった……","actor":202110,"painting":{"time":1,"alpha":0.3},"dir":1,"nameColor":"#a9f548"},{"typewriter":{"speedUp":0.01,"speed":0.05},"nameColor":"#a9f548","paintingFadeOut":{"side":0,"time":0.5},"say":"紅茶を携帯するのはメイドとして当然のことです。","actor":202120,"painting":{"time":1,"alpha":0.3},"dir":1,"side":1},{"typewriter":{"speedUp":0.01,"speed":0.05},"side":0,"say":"私だってメイドですけど…少なくともロイヤルの役職的には……","actor":202110,"painting":{"time":1,"alpha":0.3},"dir":1,"nameColor":"#a9f548"},{"typewriter":{"speedUp":0.01,"speed":0.05},"nameColor":"#a9f548","painting":{"time":1,"alpha":0.3},"say":"抹茶を味わったら、ほかの飲み物も美味しく感じますよ","actor":301121,"dir":1,"actorName":"{namecode:14}","side":1},{"typewriter":{"speedUp":0.01,"speed":0.05},"side":0,"say":"そうですか？それなら紅茶も美味しくなりそうですわね。","actor":207031,"painting":{"time":1,"alpha":0.3},"dir":1,"nameColor":"#a9f548"},{"typewriter":{"speedUp":0.01,"speed":0.05},"nameColor":"#a9f548","painting":{"time":1,"alpha":0.3},"say":"なるほどね！雷もベルファストの淹れた紅茶を飲みたい！","actor":301111,"dir":-1,"actorName":"{namecode:13}","side":1},{"typewriter":{"speedUp":0.01,"speed":0.05},"nameColor":"#a9f548","withoutPainting":true,"dir":1,"actorName":"？？？","side":2,"painting":{"time":1,"alpha":0.3},"say":"待ちなさーーい！","actor":205010},{"typewriter":{"speedUp":0.01,"speed":0.05},"side":2,"say":"あんたたち、私を誘わないのはどういうこと！？","actor":205010,"painting":{"time":1,"alpha":0.3},"dir":1,"nameColor":"#a9f548"},{"typewriter":{"speedUp":0.01,"speed":0.05},"nameColor":"#a9f548","paintingFadeOut":{"side":0,"time":0.5},"say":"あら、この前、陛下が「女王であるこの私は政務に忙しいのよ！庶民の遊びに付き合う暇なんてないわ！フン！」と仰っていましたから、てっきり……","actor":207031,"painting":{"time":1,"alpha":0.3},"dir":-1,"side":1},{"typewriter":{"speedUp":0.01,"speed":0.05},"side":0,"say":"で、でも皆でお茶会なんて…私、一人だけでさ、さびしぃ……ふ、フンだ！女王である私を歓迎すべきなのではなくて？","actor":205010,"painting":{"time":1,"alpha":0.3},"dir":1,"nameColor":"#a9f548"},{"typewriter":{"speedUp":0.01,"speed":0.05},"side":1,"say":"失礼致しました、女王陛下。私どものお茶会にお越し頂きありがたき幸せにございます。こちらにお席を用意致しましたので、どうぞお掛けくださいませ","actor":202120,"painting":{"time":1,"alpha":0.3},"dir":1,"nameColor":"#a9f548"},{"typewriter":{"speedUp":0.01,"speed":0.05},"side":0,"say":"よいっしょ……ふん！ベルが悪いのよ！ウォースパイトがいないからって、あんたが起こさないんだから朝起きられなくてお昼間まで寝たのよ！","actor":205010,"painting":{"time":1,"alpha":0.3},"dir":1,"nameColor":"#a9f548"},{"typewriter":{"speedUp":0.01,"speed":0.05},"side":1,"say":"…女王陛下の安眠を妨げるのは忍びなく、私にはとても…誠に申し訳ございません。何卒このベルファストに処罰を――","actor":202120,"painting":{"time":1,"alpha":0.3},"dir":1,"nameColor":"#a9f548"},{"typewriter":{"speedUp":0.01,"speed":0.05},"side":0,"say":"まあいいわ！これから毎日寝る前にお話を聞かせてくれたら許してあげるわ！まあ昨日寝たのが結構遅かったし。ところで私の分は？","actor":205010,"painting":{"time":1,"alpha":0.3},"dir":1,"nameColor":"#a9f548"},{"typewriter":{"speedUp":0.01,"speed":0.05},"side":1,"say":"はい！重桜の方々が用意したものもあります！ぜひご賞味ください！","actor":202110,"painting":{"time":1,"alpha":0.3},"dir":-1,"nameColor":"#a9f548"},{"flashout":{"dur":1,"alpha":[0,1],"black":true},"say":"同じ時刻、暁は――","blackBg":true,"painting":{"time":1,"alpha":0.3},"flashin":{"delay":1,"dur":1,"alpha":[1,0],"black":true},"typewriter":{"speedUp":0.01,"speed":0.05}},{"blackBg":true,"painting":{"time":1,"alpha":0.3},"typewriter":{"speedUp":0.01,"speed":0.05},"say":"【N34°E140°】"},{"typewriter":{"speedUp":0.01,"speed":0.05},"nameColor":"#a9f548","say":"一人はやっぱりちょっと……ううん――ニンジャの暁なら一人でもくじけないわ！北方連合、それがしが参るでござる！","dir":1,"actorName":"{namecode:11}","side":2,"painting":{"time":1,"alpha":0.3},"actor":301090,"blackBg":true}],"mode":2,"fadein":1.5,"id":"TEATIME2","fadeOut":1.5}