{"id":"U556STORY7","scripts":[{"stopbgm":true,"mode":1,"sequence":[["誓ってナイト！\n\n<size=45>七　約束だよ！<\/size>",1]]},{"bgmDelay":2,"flashin":{"alpha":[1,0],"delay":1,"black":true,"dur":1},"bgName":"bg_story_task","dir":1,"flashout":{"alpha":[0,1],"black":true,"dur":1},"say":"明日、一緒に海に行くって…？","nameColor":"#a9f548","bgm":"story-1","side":2,"painting":{"time":1,"alpha":0.3},"effects":[{"delay":2,"active":true,"name":"memoryFog"}],"actor":408040,"typewriter":{"speed":0.05,"speedUp":0.01}},{"bgName":"bg_story_task","dir":1,"say":"確かに約束したけど……でも本当にいいの？指揮官って忙しいでしょう？無理やりあたしに付き合わなくてもいいよ？","nameColor":"#a9f548","side":2,"expression":2,"painting":{"time":1,"alpha":0.3},"actor":408040,"typewriter":{"speed":0.05,"speedUp":0.01}},{"bgName":"bg_story_task","dir":1,"say":"「約束だから」って……じゃ、じゃあ決まりね！えへへ♪","nameColor":"#a9f548","side":2,"expression":1,"painting":{"time":1,"alpha":0.3},"actor":408040,"typewriter":{"speed":0.05,"speedUp":0.01}},{"effects":[{"name":"memoryFog","active":false}],"flashin":{"alpha":[1,0],"delay":0.5,"black":true,"dur":0.5},"bgName":"star_level_bg_106","dir":1,"flashout":{"alpha":[0,1],"black":true,"dur":0.5},"say":"海よ！あたしが来たぞー！","nameColor":"#a9f548","side":2,"painting":{"time":1,"alpha":0.3},"actor":408040,"typewriter":{"speed":0.05,"speedUp":0.01}},{"bgName":"star_level_bg_106","dir":1,"say":"あははは！","nameColor":"#a9f548","action":[{"y":-2000,"x":0,"dur":0.3,"delay":0,"type":"move"}],"side":2,"expression":1,"painting":{"time":1,"alpha":0.3},"actor":408040,"typewriter":{"speed":0.05,"speedUp":0.01}},{"bgName":"star_level_bg_106","side":2,"dir":1,"painting":{"time":1,"alpha":0.3},"say":"どぼーん、とU-556は目にも留まらぬ速さで海に飛び込んだ。","typewriter":{"speed":0.05,"speedUp":0.01}},{"painting":{"time":1,"alpha":0.3},"typewriter":{"speed":0.05,"speedUp":0.01},"bgName":"star_level_bg_106","side":2,"dir":1,"say":"指揮官、こっちこっち！","actor":408040,"nameColor":"#a9f548"},{"bgName":"star_level_bg_106","side":2,"dir":1,"painting":{"time":1,"alpha":0.3},"say":"……今日はいっぱい付き合ってあげよう。","typewriter":{"speed":0.05,"speedUp":0.01}},{"flashin":{"alpha":[1,0],"delay":0.25,"black":true,"dur":0.25},"bgName":"star_level_bg_106","dir":1,"flashout":{"alpha":[0,1],"black":true,"dur":0.25},"say":"あははは！指揮官っておっそーい！","nameColor":"#a9f548","side":2,"expression":2,"painting":{"time":1,"alpha":0.3},"actor":408040,"typewriter":{"speed":0.05,"speedUp":0.01}},{"flashin":{"alpha":[1,0],"delay":0.25,"black":true,"dur":0.25},"bgName":"star_level_bg_106","dir":1,"flashout":{"alpha":[0,1],"black":true,"dur":0.25},"say":"へい！指揮官、水鉄砲をくらえ！","nameColor":"#a9f548","action":[{"y":45,"x":0,"dur":0.2,"delay":0,"number":2,"type":"shake"}],"side":2,"expression":1,"painting":{"time":1,"alpha":0.3},"actor":408040,"typewriter":{"speed":0.05,"speedUp":0.01}},{"flashin":{"alpha":[1,0],"delay":0.25,"black":true,"dur":0.25},"bgName":"star_level_bg_106","dir":1,"flashout":{"alpha":[0,1],"black":true,"dur":0.25},"say":"指揮官、対潜攻撃に失敗！U-556の反撃ィ！","nameColor":"#a9f548","side":2,"painting":{"time":1,"alpha":0.3},"actor":408040,"typewriter":{"speed":0.05,"speedUp":0.01}},{"flashin":{"alpha":[1,0],"delay":0.5,"black":true,"dur":0.5},"bgName":"star_level_bg_106","dir":1,"flashout":{"alpha":[0,1],"black":true,"dur":0.5},"say":"あっという間に一日が終わった。","stopbgm":true,"side":2,"painting":{"time":1,"alpha":0.3},"typewriter":{"speed":0.05,"speedUp":0.01}},{"bgName":"star_level_bg_106","dir":1,"say":"指揮官と丸一日遊ぶなんて思ってなかったよ…","nameColor":"#a9f548","side":2,"expression":2,"painting":{"time":1,"alpha":0.3},"actor":408040,"typewriter":{"speed":0.05,"speedUp":0.01}},{"painting":{"time":1,"alpha":0.3},"typewriter":{"speed":0.05,"speedUp":0.01},"bgName":"star_level_bg_106","side":2,"dir":1,"say":"指揮官は楽しかった？","actor":408040,"nameColor":"#a9f548"},{"bgName":"star_level_bg_106","dir":1,"say":"えへへ、あたしも楽しかった！","nameColor":"#a9f548","side":2,"expression":1,"painting":{"time":1,"alpha":0.3},"actor":408040,"typewriter":{"speed":0.05,"speedUp":0.01}},{"painting":{"time":1,"alpha":0.3},"typewriter":{"speed":0.05,"speedUp":0.01},"bgName":"star_level_bg_106","side":2,"dir":1,"say":"ビスマルクのアネキもいればもっと楽しかったのになー","actor":408040,"nameColor":"#a9f548"},{"bgName":"star_level_bg_106","dir":1,"say":"……ねえ、指揮官、ちょっと聞いてくれるかな？","nameColor":"#a9f548","bgm":"story-2","side":2,"expression":2,"painting":{"time":1,"alpha":0.3},"actor":408040,"typewriter":{"speed":0.05,"speedUp":0.01}},{"painting":{"time":1,"alpha":0.3},"typewriter":{"speed":0.05,"speedUp":0.01},"bgName":"star_level_bg_106","side":2,"dir":1,"say":"アネキとの約束って、ただあたしが何かどうするってだけじゃなくて…","actor":408040,"nameColor":"#a9f548"},{"bgName":"star_level_bg_106","dir":1,"say":"あの約束があるから、あたしが普段とは違うアネキを見れたり、アネキもあたしの前では楽に出来たり…","nameColor":"#a9f548","side":2,"expression":1,"painting":{"time":1,"alpha":0.3},"actor":408040,"typewriter":{"speed":0.05,"speedUp":0.01}},{"bgName":"star_level_bg_106","dir":1,"say":"ひょんなことがきっかけで出来た約束かもしれないけど…でも今はあたしとアネキとを繋げるキズナなの！","nameColor":"#a9f548","side":2,"expression":2,"painting":{"time":1,"alpha":0.3},"actor":408040,"typewriter":{"speed":0.05,"speedUp":0.01}},{"bgName":"star_level_bg_106","dir":1,"say":"というわけで、指揮官、あたしたちも約束をしよう！","nameColor":"#a9f548","side":2,"expression":1,"painting":{"time":1,"alpha":0.3},"actor":408040,"typewriter":{"speed":0.05,"speedUp":0.01}},{"painting":{"time":1,"alpha":0.3},"typewriter":{"speed":0.05,"speedUp":0.01},"bgName":"star_level_bg_106","side":2,"dir":1,"say":"コホン！海の神様に誓って、指揮官がどんな危険に遭っても、いつでもどこでも駆けつけてお守りします！","actor":408040,"nameColor":"#a9f548"},{"bgName":"star_level_bg_106","dir":1,"say":"あっ、指揮官はビスマルクのアネキじゃないから、交換条件もつけさせていただきます！","nameColor":"#a9f548","side":2,"expression":3,"painting":{"time":1,"alpha":0.3},"actor":408040,"typewriter":{"speed":0.05,"speedUp":0.01}},{"painting":{"time":1,"alpha":0.3},"typewriter":{"speed":0.05,"speedUp":0.01},"bgName":"star_level_bg_106","side":2,"dir":1,"say":"ええと、U-556がいつ会いに行っても怒らないこと、そしてU-556の前から勝手にいなくならないこと！……で、いいかな？","actor":408040,"nameColor":"#a9f548"},{"bgName":"star_level_bg_106","dir":1,"say":"……","nameColor":"#a9f548","withoutActorName":true,"side":2,"painting":{"time":1,"alpha":0.3},"options":[{"content":"小指を出す","flag":1}],"actor":408040,"typewriter":{"speed":0.05,"speedUp":0.01}},{"bgName":"star_level_bg_106","dir":1,"say":"うん！じゃあ約束ね！破ったらダメだよ！","nameColor":"#a9f548","side":2,"expression":1,"painting":{"time":1,"alpha":0.3},"actor":408040,"typewriter":{"speed":0.05,"speedUp":0.01}},{"painting":{"time":1,"alpha":0.3},"bgName":"star_level_bg_106","side":2,"dir":1,"blackBg":true,"say":"絡めた二人の小指から、キズナの暖かさを感じた。","typewriter":{"speed":0.05,"speedUp":0.01}}],"fadeOut":1.5,"fadeType":2,"fadein":1.5,"mode":2,"once":true}