{"fadeType":1,"once":true,"scripts":[{"typewriter":{"speedUp":0.01,"speed":0.05},"side":2,"bgmDelay":2,"say":"NYシティ周辺海域","dir":1,"effects":[{"active":true,"name":"UIhuohua"}],"painting":{"time":1,"alpha":0.3},"bgm":"airRaidAlarm"},{"typewriter":{"speedUp":0.01,"speed":0.05},"side":2,"say":"【NYシティ】――ユニオンの最大の港にして、世界でも有数なインフラと附属施設の充実度を誇る軍港である","dir":1,"painting":{"time":1,"alpha":0.3}},{"typewriter":{"speedUp":0.01,"speed":0.05},"side":2,"say":"戦略的な要所でもあることから、【NYシティ】ではアズールレーン設立当初から司令部が設置され、NA海域における指揮系統の中心として機能してきた。","dir":1,"painting":{"time":1,"alpha":0.3}},{"typewriter":{"speedUp":0.01,"speed":0.05},"side":2,"say":"また、【NYシティ】のその周辺に浮かぶ長大な島には、人類の総力を結集した強固な防衛線が構築されている。","dir":1,"painting":{"time":1,"alpha":0.3}},{"typewriter":{"speedUp":0.01,"speed":0.05},"side":2,"say":"数々の要塞や砲台、工場と兵站、そして遊撃戦力として配属された艦隊。彼女たちが守っているのはアズールレーンの司令部と――","dir":1,"painting":{"time":1,"alpha":0.3}},{"typewriter":{"speedUp":0.01,"speed":0.05},"side":2,"say":"人類に最新技術と兵装物資を提供し、ありとあらゆる面で戦いを支える軍産複合体の大企業たちだ。","dir":1,"painting":{"time":1,"alpha":0.3}},{"typewriter":{"speedUp":0.01,"speed":0.05},"side":2,"say":"セイレーンの襲来により追い詰められた人類だったが、【NYシティ】の防衛線だけは一度たりとも抜かれることはなかった。","dir":1,"painting":{"time":1,"alpha":0.3}},{"typewriter":{"speedUp":0.01,"speed":0.05},"side":2,"say":"まさに人類の最終防衛線、何事があろうと決して抜かれることはない、そう思われていたが……","dir":1,"painting":{"time":1,"alpha":0.3}},{"typewriter":{"speedUp":0.01,"speed":0.05},"side":2,"say":"セイレーン撃退による平和、様々な勢力間の策謀、そしてレッドアクシズ――ユニオンの戦力が各地に分散したことにより、ついにセイレーンに隙を突かれる形になってしまった。","dir":1,"painting":{"time":1,"alpha":0.3}},{"typewriter":{"speedUp":0.01,"speed":0.05},"side":2,"say":"思えば、全てはセイレーンの思うがままに踊らされていたのかもしれない。","dir":1,"painting":{"time":1,"alpha":0.3}},{"typewriter":{"speedUp":0.01,"speed":0.05},"side":2,"say":"しかし、今はそうも言ってはいられない。","dir":1,"painting":{"time":1,"alpha":0.3}},{"typewriter":{"speedUp":0.01,"speed":0.05},"side":2,"say":"ユニオン、ひいてはアズールレーンの敗北は勢力間の力の均衡に影響を及ぼすだけでなく、セイレーンとの間の膠着状態を崩し、奴らの大攻勢を再び招き入れかねない","dir":1,"painting":{"time":1,"alpha":0.3}},{"typewriter":{"speedUp":0.01,"speed":0.05},"side":2,"say":"ならば、指揮官、そして彼女たちのやるべきことはたった一つ――","dir":1,"painting":{"time":1,"alpha":0.3}},{"typewriter":{"speedUp":0.01,"speed":0.05},"side":2,"say":"そんな……指揮官、私達はどうすれば…？","actor":207040,"painting":{"time":1,"alpha":0.3},"dir":1,"nameColor":"#a9f548"},{"typewriter":{"speedUp":0.01,"speed":0.05},"nameColor":"#a9f548","painting":{"time":1,"alpha":0.3},"say":"セイレーン……許さない…！","actor":103160,"dialogShake":{"x":11,"number":2,"speed":0.09},"side":2,"dir":1}],"mode":2,"fadein":1.5,"id":"XIANGTINGLIAOFA8","fadeOut":1.5}