{"fadeType":2,"once":true,"scripts":[{"mode":1,"stopbgm":true,"sequence":[["Centaur and the Port \"Elders\"\n\n<size=45>Chapter 1 - The Venerated Elder<\/size>",1]]},{"flashout":{"dur":1,"alpha":[0,1],"black":true},"say":"Port - Pier","dir":1,"bgm":"story-1","side":2,"bgmDelay":2,"typewriter":{"speedUp":0.01,"speed":0.05},"bgName":"bg_story_outdoor","flashin":{"delay":1,"dur":1,"alpha":[1,0],"black":true}},{"typewriter":{"speedUp":0.01,"speed":0.05},"side":2,"painting":{"time":1,"alpha":0.3},"say":"Today I practice drawing against the waves.","actor":206010,"dir":1,"bgName":"bg_story_outdoor","nameColor":"#a9f548"},{"typewriter":{"speedUp":0.01,"speed":0.05},"nameColor":"#a9f548","say":"It's my turn! Draw!","dir":1,"side":2,"painting":{"time":1,"alpha":0.3},"soundeffect":"event:\/battle\/plane","effects":[{"active":true,"name":"speed"}],"bgName":"bg_story_outdoor","actor":206010},{"typewriter":{"speedUp":0.01,"speed":0.05},"side":2,"say":"Hermes was in perfect form as usual.","dir":1,"effects":[{"active":false,"name":"speed"}],"bgName":"bg_story_outdoor"},{"flashout":{"dur":0.5,"alpha":[0,1],"black":true},"side":2,"options":[{"flag":1,"content":"Go see who it is."}],"say":"... Just then, I saw someone peeking her head out from behind the wall...","dir":1,"typewriter":{"speedUp":0.01,"speed":0.05},"bgName":"bg_story_outdoor","flashin":{"delay":0.5,"dur":0.5,"alpha":[1,0],"black":true}},{"expression":4,"nameColor":"#a9f548","say":"Ah! Commander! Good morning!","dir":-1,"side":2,"action":[{"type":"shake","y":45,"delay":0,"dur":0.1,"number":2,"x":0}],"painting":{"time":1,"alpha":0.3},"typewriter":{"speedUp":0.01,"speed":0.05},"bgName":"bg_story_outdoor","actor":206040},{"expression":4,"nameColor":"#a9f548","say":"Oh, I'm here doing... perfectly normal... ordinary things! You know...","dir":-1,"side":2,"painting":{"time":1,"alpha":0.3},"typewriter":{"speedUp":0.01,"speed":0.05},"bgName":"bg_story_outdoor","actor":206040},{"typewriter":{"speedUp":0.01,"speed":0.05},"side":2,"say":"I followed Centaur's line of sight all the way over to Hermes, practicing her draws.","dir":1,"bgName":"bg_story_outdoor"},{"typewriter":{"speedUp":0.01,"speed":0.05},"side":2,"painting":{"time":1,"alpha":0.3},"say":"I have a little sister whose name is also Hermes. She's named after her, the Grand Matriarch of All Aircraft Carriers. I just wanted to bear witness to her.","actor":206040,"dir":-1,"bgName":"bg_story_outdoor","nameColor":"#a9f548"},{"typewriter":{"speedUp":0.01,"speed":0.05},"side":2,"painting":{"time":1,"alpha":0.3},"say":"But I haven't been able to work up the courage to go talk to her... so I'd just as soon watch from the sidelines here...","actor":206040,"dir":-1,"bgName":"bg_story_outdoor","nameColor":"#a9f548"},{"expression":4,"nameColor":"#a9f548","say":"I don't suppose you could help me, Commander...?","dir":-1,"side":2,"action":[{"type":"shake","y":0,"delay":0,"dur":0.4,"number":2,"x":22.5}],"options":[{"flag":1,"content":"Call Hermes over."}],"painting":{"time":1,"alpha":0.3},"typewriter":{"speedUp":0.01,"speed":0.05},"bgName":"bg_story_outdoor","actor":206040},{"typewriter":{"speedUp":0.01,"speed":0.05},"nameColor":"#a9f548","say":"Waaaait?!","dir":-1,"side":2,"action":[{"type":"shake","y":45,"delay":0,"dur":0.2,"number":2,"x":0}],"painting":{"time":1,"alpha":0.3},"bgName":"bg_story_outdoor","actor":206040},{"typewriter":{"speedUp":0.01,"speed":0.05},"side":2,"painting":{"time":1,"alpha":0.3},"say":"What is it, Commander? Do you feel the urge to Duel burning within you?","actor":206010,"dir":1,"bgName":"bg_story_outdoor","nameColor":"#a9f548"},{"expression":4,"nameColor":"#a9f548","paintingFadeOut":{"side":1,"time":0.5},"say":"Um, Elder Hermes...","dir":-1,"side":0,"painting":{"time":1,"alpha":0.3},"typewriter":{"speedUp":0.01,"speed":0.05},"bgName":"bg_story_outdoor","actor":206040},{"typewriter":{"speedUp":0.01,"speed":0.05},"side":1,"painting":{"time":1,"alpha":0.3},"say":"You are... Oh! You're Centaur, our new recruit! I've heard you have a younger sister named Hermes, is that right?","actor":206010,"dir":1,"bgName":"bg_story_outdoor","nameColor":"#a9f548"},{"expression":2,"nameColor":"#a9f548","say":"Y-Yes!","dir":-1,"side":0,"action":[{"type":"shake","y":45,"delay":0,"dur":0.1,"number":2,"x":0}],"painting":{"time":1,"alpha":0.3},"typewriter":{"speedUp":0.01,"speed":0.05},"bgName":"bg_story_outdoor","actor":206040},{"typewriter":{"speedUp":0.01,"speed":0.05},"side":2,"say":"Centaur let out a sigh of relief.","dir":1,"bgName":"bg_story_outdoor"},{"typewriter":{"speedUp":0.01,"speed":0.05},"side":1,"painting":{"time":1,"alpha":0.3},"say":"Come then! Let's test your mettle in a duel!","actor":206010,"dir":1,"bgName":"bg_story_outdoor","nameColor":"#a9f548"},{"typewriter":{"speedUp":0.01,"speed":0.05},"side":1,"painting":{"time":1,"alpha":0.3},"say":"Commander, I'll be borrowing this one for a bit!","actor":206010,"dir":1,"bgName":"bg_story_outdoor","nameColor":"#a9f548"},{"expression":4,"nameColor":"#a9f548","say":"Huh? Where? What?!","dir":-1,"subActors":[{"actor":206010,"pos":{"x":-675}}],"side":2,"action":[{"type":"shake","y":45,"delay":0,"dur":0.1,"number":2,"x":0},{"type":"move","y":0,"delay":0.5,"dur":1,"x":2250}],"painting":{"time":1,"alpha":0.3},"typewriter":{"speedUp":0.01,"speed":0.05},"bgName":"bg_story_outdoor","actor":206040},{"typewriter":{"speedUp":0.01,"speed":0.05},"side":2,"say":"Hermes started dragging Centaur off somewhere.","dir":1,"bgName":"bg_story_outdoor"},{"typewriter":{"speedUp":0.01,"speed":0.05},"side":2,"say":"She would grow accustomed to Hermes's eccentricities in time... probably.","dir":1,"bgName":"bg_story_outdoor","blackBg":true}],"mode":2,"fadein":1.5,"id":"BANRENMA1","fadeOut":1.5}