{"fadein":1.5,"once":true,"id":"FENGBAOQIANXI10","fadeType":1,"mode":2,"fadeOut":1.5,"scripts":[{"side":1,"say":"Now THAT was a battle! We admit defeat.","bgm":"level","nameColor":"#a9f548","typewriter":{"speedUp":0.01,"speed":0.05},"dir":-1,"painting":{"time":1,"alpha":0.3},"actor":205060},{"side":1,"typewriter":{"speedUp":0.01,"speed":0.05},"nameColor":"#a9f548","say":"It definitely was. You predicted our attacking fleet's position and countered like it was nothing. Now I can see why you've earned the nickname \"Big E.\"","dir":1,"painting":{"time":1,"alpha":0.3},"actor":207020},{"side":0,"typewriter":{"speedUp":0.01,"speed":0.05},"nameColor":"#a9f548","say":"I'm honored, but I alone don't deserve all the credit. I couldn't have done it without the rest of the fleet.","dir":-1,"painting":{"time":1,"alpha":0.3},"actor":107060},{"side":0,"typewriter":{"speedUp":0.01,"speed":0.05},"nameColor":"#a9f548","say":"... By the way, we've been saying goodbye for quite some time now. You should probably get going soon. Hopefully, we'll get another chance to fight like this in the future.","dir":-1,"painting":{"time":1,"alpha":0.3},"actor":107060},{"side":1,"typewriter":{"speedUp":0.01,"speed":0.05},"nameColor":"#a9f548","say":"I'm sure it won't be long until it comes, at least if this war with the Sirens continues.","dir":-1,"painting":{"time":1,"alpha":0.3},"actor":205060},{"side":0,"typewriter":{"speedUp":0.01,"speed":0.05},"nameColor":"#a9f548","say":"Funny you mention that. I was just gonna offer you an escort through the higher-risk waters. Lots of Sirens in some places.","dir":-1,"painting":{"time":1,"alpha":0.3},"actor":107060},{"side":1,"typewriter":{"speedUp":0.01,"speed":0.05},"nameColor":"#a9f548","say":"Thanks, but we'll be fine. If any show up, they'll serve as morale-boosting victories after our defeat against you.","dir":-1,"painting":{"time":1,"alpha":0.3},"actor":205060},{"side":1,"typewriter":{"speedUp":0.01,"speed":0.05},"nameColor":"#a9f548","say":"Moreover, ensuring the safety of NY City should be your highest priority. You don't need to worry about us.","dir":-1,"painting":{"time":1,"alpha":0.3},"actor":205060},{"side":1,"typewriter":{"speedUp":0.01,"speed":0.05},"nameColor":"#a9f548","say":"It is my honour and duty to clean up any pests that impede our travels. Please, allow me to take care of it.","dir":-1,"painting":{"time":1,"alpha":0.3},"actor":202080},{"side":2,"typewriter":{"speedUp":0.01,"speed":0.05},"nameColor":"#a9f548","say":"All right, if you say so. Good luck, everyone!","dir":-1,"painting":{"time":1,"alpha":0.3},"actor":107060},{"side":2,"typewriter":{"speedUp":0.01,"speed":0.05},"nameColor":"#a9f548","say":"Likewise. May Lady Luck smile upon the Eagle Union.","dir":-1,"painting":{"time":1,"alpha":0.3},"actor":205060},{"typewriter":{"speedUp":0.01,"speed":0.05},"flashin":{"black":true,"delay":0.5,"dur":0.5,"alpha":[1,0]},"side":2,"stopbgm":true,"painting":{"time":1,"alpha":0.3},"nameColor":"#a9f548","flashout":{"black":true,"dur":0.5,"alpha":[0,1]},"dir":-1,"say":"... I know this ill-boding feeling all too well...","actor":205060},{"side":2,"typewriter":{"speedUp":0.01,"speed":0.05},"nameColor":"#a9f548","say":"Attention, everyone! We must head home and report to Her Majesty immediately!","dir":-1,"painting":{"time":1,"alpha":0.3},"actor":205060}]}