{"fadeType":2,"once":true,"scripts":[{"mode":1,"stopbgm":true,"sequence":[["I'm Not A Baby!\n\n<size=45>Chapter 6 - I'm A Grownup!<\/size>",1]]},{"flashout":{"dur":1,"alpha":[0,1],"black":true},"say":"Port - Commander's Office","dir":1,"bgm":"story-1","side":2,"bgmDelay":2,"typewriter":{"speedUp":0.01,"speed":0.05},"bgName":"bg_story_task","flashin":{"delay":1,"dur":1,"alpha":[1,0],"black":true}},{"typewriter":{"speedUp":0.01,"speed":0.05},"side":2,"say":"So far it's been a normal day without any–","dir":1,"bgName":"bg_story_task","painting":{"time":1,"alpha":0.3}},{"side":2,"painting":{"time":1,"alpha":0.3},"say":"<size=60>Commander, go on a date with me!<\/size>","actor":108030,"dir":1,"bgName":"bg_story_task","nameColor":"#a9f548"},{"typewriter":{"speedUp":0.01,"speed":0.05},"side":2,"say":"……？","dir":1,"bgName":"bg_story_task","painting":{"time":1,"alpha":0.3}},{"typewriter":{"speedUp":0.01,"speed":0.05},"side":2,"say":"(W-what did she just say?)","dir":1,"painting":{"time":1,"alpha":0.3},"bgName":"bg_story_task","dialogShake":{"x":8.5,"number":2,"speed":0.09}},{"expression":2,"nameColor":"#a9f548","say":"Commander, didn't you hear me? Date! With me!","dir":1,"side":2,"painting":{"time":1,"alpha":0.3},"typewriter":{"speedUp":0.01,"speed":0.05},"bgName":"bg_story_task","actor":108030},{"typewriter":{"speedUp":0.01,"speed":0.05},"side":2,"say":"(Calm down, me. Prime numbers, prime numbers...)","dir":1,"options":[{"flag":1,"content":"Ask her why she wants a \"date\""}],"bgName":"bg_story_task","painting":{"time":1,"alpha":0.3}},{"typewriter":{"speedUp":0.01,"speed":0.05},"side":2,"painting":{"time":1,"alpha":0.3},"say":"Shoukaku told me about it!","actor":108030,"dir":1,"bgName":"bg_story_task","nameColor":"#a9f548"},{"expression":2,"nameColor":"#a9f548","say":"She said, \"the Commander won't think you're a baby anymore if you go on a date\"!","dir":1,"side":2,"painting":{"time":1,"alpha":0.3},"typewriter":{"speedUp":0.01,"speed":0.05},"bgName":"bg_story_task","actor":108030},{"typewriter":{"speedUp":0.01,"speed":0.05},"side":2,"painting":{"time":1,"alpha":0.3},"say":"Although I'm not really sure what a \"date\" is...","actor":108030,"dir":1,"bgName":"bg_story_task","nameColor":"#a9f548"},{"expression":5,"nameColor":"#a9f548","say":"Point is: you think I'm just a baby, that's why you always act so cautious around me!","dir":1,"side":2,"painting":{"time":1,"alpha":0.3},"typewriter":{"speedUp":0.01,"speed":0.05},"bgName":"bg_story_task","actor":108030},{"expression":4,"nameColor":"#a9f548","say":"And it makes me mad!","dir":1,"side":2,"painting":{"time":1,"alpha":0.3},"typewriter":{"speedUp":0.01,"speed":0.05},"bgName":"bg_story_task","actor":108030},{"typewriter":{"speedUp":0.01,"speed":0.05},"nameColor":"#a9f548","say":"So, go on a date with me! Then, I'll show you a part of me you've never seen before!","dir":1,"side":2,"action":[{"type":"shake","y":30,"delay":0,"dur":0.15,"number":2,"x":0}],"painting":{"time":1,"alpha":0.3},"bgName":"bg_story_task","actor":108030},{"expression":4,"nameColor":"#a9f548","say":"... Please?","dir":1,"side":2,"options":[{"flag":1,"content":"Agree"},{"flag":2,"content":"Refuse"}],"painting":{"time":1,"alpha":0.3},"typewriter":{"speedUp":0.01,"speed":0.05},"bgName":"bg_story_task","actor":108030},{"expression":4,"nameColor":"#a9f548","say":"I'm not leaving until you say \"yes\"!","dir":1,"painting":{"time":1,"alpha":0.3},"side":2,"action":[{"type":"shake","y":45,"delay":0,"dur":0.15,"number":2,"x":0}],"options":[{"flag":3,"content":"Agree"}],"typewriter":{"speedUp":0.01,"speed":0.05},"actor":108030,"bgName":"bg_story_task","optionFlag":2},{"expression":2,"nameColor":"#a9f548","say":"Great!","dir":1,"side":2,"painting":{"time":1,"alpha":0.3},"typewriter":{"speedUp":0.01,"speed":0.05},"bgName":"bg_story_task","actor":108030},{"typewriter":{"speedUp":0.01,"speed":0.05},"side":2,"painting":{"time":1,"alpha":0.3},"say":"Um, Shoukaku didn't teach me what you do on a date... So let's just go out and have fun.","actor":108030,"dir":1,"bgName":"bg_story_task","nameColor":"#a9f548"},{"typewriter":{"speedUp":0.01,"speed":0.05},"side":2,"say":"(Yup. I knew this is how things would turn out one day...)","dir":1,"painting":{"time":1,"alpha":0.3},"bgName":"bg_story_task","blackBg":true}],"mode":2,"fadein":1.5,"id":"JIQI6","fadeOut":1.5}