{"fadein":1.5,"once":true,"fadeType":1,"mode":2,"id":"MAOZIHUODONG26","scripts":[{"actorName":"？？？","bgName":"bg_cccp_7","typewriter":{"speedUp":0.01,"speed":0.05},"painting":{"time":1,"alpha":0.3},"side":2,"bgm":"xinnong-2","nameColor":"#ff5c5c","dir":1,"say":"The enemies have come to challenge me... and these insects have embraced evil... How ignorant, how foolish!"},{"actorName":"？？？","bgName":"bg_cccp_7","typewriter":{"speedUp":0.01,"speed":0.05},"nameColor":"#ff5c5c","say":"What they shall find at the core, Deus ex Machina, shall put an end to their journey!","dir":1,"painting":{"time":1,"alpha":0.3},"side":2},{"actorName":"？？？","bgName":"bg_cccp_7","typewriter":{"speedUp":0.01,"speed":0.05},"nameColor":"#ff5c5c","say":"Give yourself to fear, for the end is nigh!!","dir":1,"painting":{"time":1,"alpha":0.3},"side":2},{"bgName":"bg_cccp_7","typewriter":{"speedUp":0.01,"speed":0.05},"painting":{"time":1,"alpha":0.3},"side":2,"nameColor":"#a9f548","expression":3,"dir":1,"say":"...Is that so? The hell are you talking about? Are you trying to sound cool?","actor":701040},{"actorName":"？？？","bgName":"bg_cccp_7","typewriter":{"speedUp":0.01,"speed":0.05},"nameColor":"#ff5c5c","say":".........","dir":1,"painting":{"time":1,"alpha":0.3},"side":2},{"bgName":"bg_cccp_7","typewriter":{"speedUp":0.01,"speed":0.05},"painting":{"time":1,"alpha":0.3},"side":2,"nameColor":"#a9f548","expression":3,"dir":1,"say":"Come out already. That script you're reading from is lame.","actor":701040},{"actorName":"？？？","bgName":"bg_cccp_7","typewriter":{"speedUp":0.01,"speed":0.05},"nameColor":"#ff5c5c","say":".........","dir":1,"painting":{"time":1,"alpha":0.3},"side":2},{"bgName":"bg_cccp_7","typewriter":{"speedUp":0.01,"speed":0.05},"painting":{"time":1,"alpha":0.3},"side":2,"nameColor":"#a9f548","expression":3,"dir":1,"say":"Tashkent, do you know what she's talking about?","actor":702030},{"bgName":"bg_cccp_7","typewriter":{"speedUp":0.01,"speed":0.05},"painting":{"time":1,"alpha":0.3},"side":2,"nameColor":"#a9f548","expression":5,"dir":1,"say":"Don't just skulk about in the shadows, Siren! Come out and give us a fair fight!","actor":705050},{"actorName":"？？？","bgName":"bg_cccp_7","typewriter":{"speedUp":0.01,"speed":0.05},"dialogShake":{"number":2,"x":8.5,"speed":0.09},"painting":{"time":1,"alpha":0.3},"side":2,"nameColor":"#ff5c5c","dir":1,"say":"Gahaha... You asked for it!"},{"side":2,"bgName":"bg_cccp_7","typewriter":{"speedUp":0.01,"speed":0.05},"say":"(CREEAAAAAKKKK...!!)","dialogShake":{"number":2,"x":8.5,"speed":0.09},"dir":1,"painting":{"time":1,"alpha":0.3}},{"bgName":"bg_cccp_7","typewriter":{"speedUp":0.01,"speed":0.05},"painting":{"time":1,"alpha":0.3},"side":2,"action":[{"number":2,"x":0,"type":"shake","delay":0,"dur":0.15,"y":30}],"nameColor":"#a9f548","expression":4,"dir":1,"say":"What the heck is that...","actor":702020},{"side":2,"bgName":"bg_cccp_5","typewriter":{"speedUp":0.01,"speed":0.05},"say":"The ice walls cracked and split apart as a massive mechanical device began to stir, changing into a different form.","dir":1,"painting":{"time":1,"alpha":0.3}},{"side":2,"bgName":"bg_cccp_5","typewriter":{"speedUp":0.01,"speed":0.05},"say":"A giant dome rose over the icy waters and blocked out the light...","dir":1,"painting":{"time":1,"alpha":0.3}},{"side":2,"bgName":"bg_cccp_5","typewriter":{"speedUp":0.01,"speed":0.05},"say":"What in the world... is this...?!","dir":1,"painting":{"time":1,"alpha":0.3}},{"actorName":"？？？","bgName":"bg_cccp_5","typewriter":{"speedUp":0.01,"speed":0.05},"nameColor":"#ff5c5c","say":"\"The king dons his Crown, the flowers are in full bloom, and the souls return to the seas. Thus begins the Overture of the End!\"","dir":1,"painting":{"time":1,"alpha":0.3},"side":2},{"actorName":"？？？","bgName":"bg_cccp_5","typewriter":{"speedUp":0.01,"speed":0.05},"nameColor":"#ff5c5c","say":"Every finale gives way to a new overture, as destruction gives way to new life. I am \"Omitter.\"","dir":1,"painting":{"time":1,"alpha":0.3},"side":2},{"actorName":"Omitter","bgName":"bg_cccp_7","typewriter":{"speedUp":0.01,"speed":0.05},"nameColor":"#ff5c5c","say":"I am the one who rules over these seas!","dir":1,"painting":{"time":1,"alpha":0.3},"side":2},{"side":2,"bgName":"bg_cccp_5","typewriter":{"speedUp":0.01,"speed":0.05},"say":"The Siren who masterminds these Mirror Seas has appeared before us.","dir":1,"painting":{"time":1,"alpha":0.3}},{"actorName":"Minsk","bgName":"bg_cccp_5","typewriter":{"speedUp":0.01,"speed":0.05},"nameColor":"#a9f548","say":"...I don't recognize her rigging...! Is she in the Eagle Union's database?!","dir":1,"painting":{"time":1,"alpha":0.3},"side":2},{"actorName":"Gangut","bgName":"bg_cccp_5","typewriter":{"speedUp":0.01,"speed":0.05},"nameColor":"#a9f548","say":"Good, it isn't a proper finale without a high-ranking boss!","dir":1,"painting":{"time":1,"alpha":0.3},"side":2},{"actorName":"Grozny","bgName":"bg_cccp_5","typewriter":{"speedUp":0.01,"speed":0.05},"nameColor":"#a9f548","say":"If we defeat her, we can get rid of this Mirror Sea...","dir":1,"painting":{"time":1,"alpha":0.3},"side":2},{"actorName":"Avrora","bgName":"bg_cccp_5","typewriter":{"speedUp":0.01,"speed":0.05},"nameColor":"#a9f548","say":"(There's something different about her compared to the other Sirens we've fought before...)","dir":1,"painting":{"time":1,"alpha":0.3},"side":2},{"actorName":"Omitter","bgName":"bg_cccp_5","typewriter":{"speedUp":0.01,"speed":0.05},"nameColor":"#ff5c5c","say":"Ahahaha! I like the looks of your faces! Yes, that's the performance that They desire!","dir":1,"painting":{"time":1,"alpha":0.3},"side":2},{"actorName":"Omitter","bgName":"bg_cccp_5","typewriter":{"speedUp":0.01,"speed":0.05},"nameColor":"#ff5c5c","say":"Let's see what it says next... \"My name shall be carved into your souls as you spend the rest of eternity trembling at the bottom of the abyss!\"","dir":1,"painting":{"time":1,"alpha":0.3},"side":2},{"actorName":"Omitter","bgName":"bg_cccp_5","typewriter":{"speedUp":0.01,"speed":0.05},"nameColor":"#ff5c5c","say":"That's so lame, it's cool! Ahahahaha!","dir":1,"painting":{"time":1,"alpha":0.3},"side":2},{"side":2,"say":"What a cheeky brat. Can I beat her up, dear comrade?","typewriter":{"speedUp":0.01,"speed":0.05},"nameColor":"#a9f548","expression":3,"dir":1,"painting":{"time":1,"alpha":0.3},"actor":701040},{"side":2,"typewriter":{"speedUp":0.01,"speed":0.05},"nameColor":"#a9f548","say":"Unfortunately, your idle threats mean nothing to the Northern Parliament!","dir":1,"painting":{"time":1,"alpha":0.3},"actor":900217},{"side":2,"typewriter":{"speedUp":0.01,"speed":0.05},"nameColor":"#ff5c5c","say":"What?! Impossible...!!","dir":1,"painting":{"time":1,"alpha":0.3},"actor":900219},{"typewriter":{"speedUp":0.01,"speed":0.05},"dialogShake":{"number":2,"x":8.5,"speed":0.09},"painting":{"time":1,"alpha":0.3},"side":2,"action":[{"number":3,"x":0,"type":"shake","delay":0,"dur":0.1,"y":30}],"nameColor":"#ff5c5c","dir":1,"say":"You assholes!! You won't even play along with me for a few minutes!! Unforgivable!!!!","actor":900219},{"side":2,"typewriter":{"speedUp":0.01,"speed":0.05},"nameColor":"#a9f548","say":"She's coming at us!","dir":1,"painting":{"time":1,"alpha":0.3},"actor":701030},{"side":2,"say":"Everyone, be on your guard!","typewriter":{"speedUp":0.01,"speed":0.05},"nameColor":"#a9f548","expression":5,"dir":1,"painting":{"time":1,"alpha":0.3},"actor":705050}]}