{"fadein":1.5,"once":true,"id":"TEACHER5","fadeType":2,"mode":2,"fadeOut":1.5,"scripts":[{"stopbgm":true,"sequence":[["Class Z V\n\n<size=45>The Melancholy of Z23<\/size>",1]],"mode":1},{"bgName":"bg_story_school","typewriter":{"speedUp":0.01,"speed":0.05},"painting":{"time":1,"alpha":0.3},"side":2,"bgm":"story-1","nameColor":"#a9f548","dir":1,"say":"Uuugh... why won't things ever work out?","actor":401230},{"side":2,"bgName":"bg_story_school","typewriter":{"speedUp":0.01,"speed":0.05},"nameColor":"#a9f548","say":"Maybe... I'm just a powerless student after all...","dir":1,"painting":{"time":1,"alpha":0.3},"actor":401230},{"bgName":"bg_story_school","typewriter":{"speedUp":0.01,"speed":0.05},"painting":{"time":1,"alpha":0.3},"side":1,"say":"Oh my... it seems that I've come across a child who needs some illustrious guidance~","paintingFadeOut":{"time":0.5,"side":0},"dir":1,"nameColor":"#a9f548","actor":207030},{"side":0,"bgName":"bg_story_school","typewriter":{"speedUp":0.01,"speed":0.05},"nameColor":"#a9f548","say":"I-Illustrious? Uwaahh...","dir":1,"painting":{"time":1,"alpha":0.3},"actor":401230},{"side":1,"bgName":"bg_story_school","typewriter":{"speedUp":0.01,"speed":0.05},"nameColor":"#a9f548","say":"There, there... let me help get this burden off your chest~","dir":1,"painting":{"time":1,"alpha":0.3},"actor":207030},{"side":0,"bgName":"bg_story_school","typewriter":{"speedUp":0.01,"speed":0.05},"nameColor":"#a9f548","say":"So... the situation is like this...","dir":1,"painting":{"time":1,"alpha":0.3},"actor":401230},{"bgName":"bg_story_school","typewriter":{"speedUp":0.01,"speed":0.05},"flashin":{"black":true,"delay":1,"dur":1,"alpha":[1,0]},"side":2,"painting":{"time":1,"alpha":0.3},"nameColor":"#a9f548","flashout":{"black":true,"dur":1,"alpha":[0,1]},"dir":1,"say":"So that's what's going on. Ahh, all the kids are so energetic~","actor":207030},{"bgName":"bg_story_school","typewriter":{"speedUp":0.01,"speed":0.05},"painting":{"time":1,"alpha":0.3},"side":0,"say":"Ener... getic...","paintingFadeOut":{"time":0.5,"side":1},"dir":1,"nameColor":"#a9f548","actor":401230},{"side":1,"bgName":"bg_story_school","typewriter":{"speedUp":0.01,"speed":0.05},"nameColor":"#a9f548","say":"How could there be any bad children in this naval base? If you try to put yourself in their shoes more and become a part of their lives, who is to say that the problems won't resolve themselves?","dir":1,"painting":{"time":1,"alpha":0.3},"actor":207030},{"side":0,"bgName":"bg_story_school","typewriter":{"speedUp":0.01,"speed":0.05},"nameColor":"#a9f548","say":"Become a part of their lives...","dir":1,"painting":{"time":1,"alpha":0.3},"actor":401230},{"side":1,"bgName":"bg_story_school","typewriter":{"speedUp":0.01,"speed":0.05},"nameColor":"#a9f548","say":"Zed, do you truly wish to help them from the bottom of your heart? If that is the case, surely you will be able to find common ground with them.","dir":1,"painting":{"time":1,"alpha":0.3},"actor":207030},{"side":0,"bgName":"bg_story_school","typewriter":{"speedUp":0.01,"speed":0.05},"nameColor":"#a9f548","say":"I... I understand now. One more... I'll give it one more try!","dir":1,"painting":{"time":1,"alpha":0.3},"actor":401230},{"side":1,"bgName":"bg_story_school","typewriter":{"speedUp":0.01,"speed":0.05},"nameColor":"#a9f548","say":"Ahh... good girl~ I'll be cheering you on~","dir":1,"painting":{"time":1,"alpha":0.3},"actor":207030}]}