{"fadeType":1,"once":true,"scripts":[{"typewriter":{"speedUp":0.01,"speed":0.05},"nameColor":"#ff5c5c","say":"... ... ...","dir":1,"actorName":"？？？","bgm":"story-6","side":2,"painting":{"time":1,"alpha":0.3},"actor":900072},{"typewriter":{"speedUp":0.01,"speed":0.05},"nameColor":"#ff5c5c","painting":{"time":1,"alpha":0.3},"say":"Why did you come here?","actor":900072,"dir":1,"actorName":"？？？","side":2},{"typewriter":{"speedUp":0.01,"speed":0.05},"side":2,"say":"Are you the \"mysterious ship\" the report mentioned?","actor":107060,"painting":{"time":1,"alpha":0.3},"dir":1,"nameColor":"#a9f548"},{"typewriter":{"speedUp":0.01,"speed":0.05},"side":2,"say":"In the Mirror Seas, you broke through the Sirens' forces in order to save one of our fleets.","actor":107060,"painting":{"time":1,"alpha":0.3},"dir":1,"nameColor":"#a9f548"},{"typewriter":{"speedUp":0.01,"speed":0.05},"side":2,"say":"However, to our surprise, we also saw you leading the Sirens during the attack on NY City.","actor":107060,"painting":{"time":1,"alpha":0.3},"dir":1,"nameColor":"#a9f548"},{"typewriter":{"speedUp":0.01,"speed":0.05},"side":2,"say":"And now, following the Winter's Crown incident, you once again seem to be involved with this singularity.","actor":107060,"painting":{"time":1,"alpha":0.3},"dir":1,"nameColor":"#a9f548"},{"typewriter":{"speedUp":0.01,"speed":0.05},"side":2,"say":"... Just who are you, exactly?","actor":107060,"painting":{"time":1,"alpha":0.3},"dir":1,"nameColor":"#a9f548"}],"mode":2,"fadein":1.5,"id":"XIANGTINGLIAOFA28","fadeOut":1.5}