{"once":true,"fadein":1.5,"updateOnBegin":1,"id":"ZHONGQIU7","fadeType":1,"mode":2,"fadeOut":1.5,"scripts":[{"side":2,"typewriter":{"speedUp":0.01,"speed":0.05},"nameColor":"#a9f548","say":"So, the first flower goes to... Prince of Wales! There you go, write down your wishes here.","dir":1,"painting":{"time":1,"alpha":0.3},"actor":502010},{"side":1,"paintingFadeOut":{"time":0.5,"side":0},"typewriter":{"speedUp":0.01,"speed":0.05},"nameColor":"#a9f548","say":"Emmm….do I have to write it in front of everyone?","dir":-1,"painting":{"time":1,"alpha":0.3},"actor":205060},{"side":0,"typewriter":{"speedUp":0.01,"speed":0.05},"nameColor":"#a9f548","say":"Hmm? Is there something that you can’t tell us?","dir":1,"painting":{"time":1,"alpha":0.3},"actor":403030},{"side":1,"typewriter":{"speedUp":0.01,"speed":0.05},"nameColor":"#a9f548","say":"Haha~ of course note, I’ll write it then --- “I hope that every girl can show her true smile”...OK!","dir":-1,"painting":{"time":1,"alpha":0.3},"actor":205060},{"typewriter":{"speedUp":0.01,"speed":0.05},"flashin":{"black":true,"delay":1,"dur":1,"alpha":[1,0]},"side":2,"painting":{"time":1,"alpha":0.3},"nameColor":"#a9f548","flashout":{"black":true,"dur":1,"alpha":[0,1]},"dir":1,"say":"Z46! Here, write something~","actor":502010},{"side":1,"paintingFadeOut":{"time":0.5,"side":0},"typewriter":{"speedUp":0.01,"speed":0.05},"nameColor":"#a9f548","say":"...I hope that everyone on Azur Lane can get the chance to relax...","dir":-1,"painting":{"time":1,"alpha":0.3},"actor":401460},{"side":1,"typewriter":{"speedUp":0.01,"speed":0.05},"nameColor":"#a9f548","say":"Wow, such pretty handwriting!","dir":-1,"painting":{"time":1,"alpha":0.3},"actor":205060},{"side":0,"typewriter":{"speedUp":0.01,"speed":0.05},"nameColor":"#a9f548","say":"Sara sit still, the next round will start soon! This time I must...","dir":1,"painting":{"time":1,"alpha":0.3},"actor":107020},{"typewriter":{"speedUp":0.01,"speed":0.05},"flashin":{"black":true,"delay":1,"dur":0.75,"alpha":[1,0]},"side":2,"painting":{"time":1,"alpha":0.3},"nameColor":"#a9f548","flashout":{"black":true,"dur":0.75,"alpha":[0,1]},"dir":1,"say":"Saratoga --- You write, too!","actor":502010},{"side":1,"paintingFadeOut":{"time":0.5,"side":0},"typewriter":{"speedUp":0.01,"speed":0.05},"nameColor":"#a9f548","say":"“I hope I get to experience more interesting things” --- OK!","dir":-1,"painting":{"time":1,"alpha":0.3},"actor":107030},{"side":0,"typewriter":{"speedUp":0.01,"speed":0.05},"nameColor":"#a9f548","say":"Shouldn’t you be writing well-wishes for your fellow shipgirls?","dir":1,"painting":{"time":1,"alpha":0.3},"actor":107020},{"side":1,"typewriter":{"speedUp":0.01,"speed":0.05},"nameColor":"#a9f548","say":"Hmm? Then isn’t being able to get together with all of you the most interesting thing ever!","dir":-1,"painting":{"time":1,"alpha":0.3},"actor":107030},{"typewriter":{"speedUp":0.01,"speed":0.05},"flashin":{"black":true,"delay":1,"dur":0.75,"alpha":[1,0]},"side":2,"painting":{"time":1,"alpha":0.3},"nameColor":"#a9f548","flashout":{"black":true,"dur":0.75,"alpha":[0,1]},"dir":1,"say":"Lastly --- Yat Sen! Hehe, it’s my turn this time~","actor":502010},{"side":2,"typewriter":{"speedUp":0.01,"speed":0.05},"nameColor":"#a9f548","say":"So...what should I write then?","dir":1,"painting":{"time":1,"alpha":0.3},"actor":502010},{"side":2,"typewriter":{"speedUp":0.01,"speed":0.05},"nameColor":"#a9f548","say":"“I hope that everyone will get new clothes for next year”...let’s say that!","dir":1,"painting":{"time":1,"alpha":0.3},"actor":502010},{"side":1,"paintingFadeOut":{"time":0.5,"side":0},"typewriter":{"speedUp":0.01,"speed":0.05},"nameColor":"#a9f548","say":"New clothes... there are those who also like to wear uniforms...","dir":-1,"painting":{"time":1,"alpha":0.3},"actor":205060},{"side":0,"typewriter":{"speedUp":0.01,"speed":0.05},"nameColor":"#a9f548","say":"……","dir":1,"painting":{"time":1,"alpha":0.3},"actor":403030},{"typewriter":{"speedUp":0.01,"speed":0.05},"flashin":{"black":true,"delay":1,"dur":0.75,"alpha":[1,0]},"side":2,"painting":{"time":1,"alpha":0.3},"nameColor":"#a9f548","flashout":{"black":true,"dur":0.75,"alpha":[0,1]},"dir":1,"say":"Second place goes to... Eugen!","actor":502010},{"side":1,"paintingFadeOut":{"time":0.5,"side":0},"typewriter":{"speedUp":0.01,"speed":0.05},"nameColor":"#a9f548","say":"Hmmm, I’ve been given a second place?!","dir":-1,"painting":{"time":1,"alpha":0.3},"actor":403030},{"side":1,"typewriter":{"speedUp":0.01,"speed":0.05},"nameColor":"#a9f548","say":"Then…”I hope to be able to get together with my sisters”, is that ok?","dir":-1,"painting":{"time":1,"alpha":0.3},"actor":403030},{"side":0,"typewriter":{"speedUp":0.01,"speed":0.05},"nameColor":"#a9f548","say":"I feel like suddenly thinking out loud “ha!” ...","dir":1,"painting":{"time":1,"alpha":0.3},"actor":205060},{"typewriter":{"speedUp":0.01,"speed":0.05},"flashin":{"black":true,"delay":1,"dur":0.75,"alpha":[1,0]},"side":2,"painting":{"time":1,"alpha":0.3},"nameColor":"#a9f548","flashout":{"black":true,"dur":0.75,"alpha":[0,1]},"dir":1,"say":"Finally, the first place... Ning Hai!","actor":502010},{"actorName":"Ning Hai","paintingFadeOut":{"time":0.5,"side":0},"typewriter":{"speedUp":0.01,"speed":0.05},"painting":{"time":1,"alpha":0.3},"side":1,"say":"What!? I'm the first place! Great!","dir":-1,"nameColor":"#a9f548","actor":502022},{"side":0,"actorName":"Ping Hai","typewriter":{"speedUp":0.01,"speed":0.05},"nameColor":"#a9f548","say":"I wanna be on the first place as well...","dir":-1,"painting":{"time":1,"alpha":0.3},"actor":502032},{"side":0,"typewriter":{"speedUp":0.01,"speed":0.05},"nameColor":"#a9f548","say":"So, Ning Hai, have you decided on your wish?","dir":1,"painting":{"time":1,"alpha":0.3},"actor":502010},{"side":1,"actorName":"Ning Hai","typewriter":{"speedUp":0.01,"speed":0.05},"nameColor":"#a9f548","say":"Yes, from the very beginning... I wish more and more friends will join us!","dir":-1,"painting":{"time":1,"alpha":0.3},"actor":502022},{"typewriter":{"speedUp":0.01,"speed":0.05},"flashin":{"black":true,"delay":1,"dur":0.75,"alpha":[1,0]},"side":2,"painting":{"time":1,"alpha":0.3},"nameColor":"#a9f548","flashout":{"black":true,"dur":0.75,"alpha":[0,1]},"dir":-1,"say":"All the lanterns flew away, out of our reach.","actor":205060},{"side":0,"paintingFadeOut":{"time":0.5,"side":1},"typewriter":{"speedUp":0.01,"speed":0.05},"nameColor":"#a9f548","say":"Yet the moon is still up there, looking over all of us. No matter how far the distance, we share the same beautiful scene with those we care but cannot be together...","dir":1,"painting":{"time":1,"alpha":0.3},"actor":502010},{"side":1,"typewriter":{"speedUp":0.01,"speed":0.05},"nameColor":"#a9f548","say":"I hope that one day all of us will be as whole and complete as the full moon tonight, all sitting together side by side...","dir":1,"painting":{"time":1,"alpha":0.3},"actor":102050},{"side":0,"typewriter":{"speedUp":0.01,"speed":0.05},"nameColor":"#a9f548","say":"Whether it’s next year or the year after, as long as I’m around, I will always come to celebrate. I haven’t had enough of this osmanthus wine!","dir":-1,"painting":{"time":1,"alpha":0.3},"actor":102090},{"side":1,"typewriter":{"speedUp":0.01,"speed":0.05},"nameColor":"#a9f548","say":"So... Let us pray to the Moon Goddess together.","dir":-1,"painting":{"time":1,"alpha":0.3},"actor":502010},{"side":1,"typewriter":{"speedUp":0.01,"speed":0.05},"nameColor":"#a9f548","say":"Wish today's joy will reunit us here every year. Wish never will we be alone in the sea, and be defeated by pain and failure... Wish everyone start understanding each other... Wish we can hold our hands forever...","dir":-1,"painting":{"time":1,"alpha":0.3},"actor":502010}]}